{
  "id": "radiating-displacement",
  "name": "Radiating Displacement",
  "url": "shaders/radiating-displacement.wgsl",
  "category": "image",
  "description": "Rippling displacement waves emanate only from strong colours; neutrals stay sharp. Mouse-click to seed ripples.",
  "params": [
    {
      "id": "speed",
      "name": "Wave Speed",
      "default": 0.5,
      "min": 0.0,
      "max": 1.0
    },
    {
      "id": "strength",
      "name": "Displace Strength",
      "default": 0.5,
      "min": 0.0,
      "max": 1.0
    },
    {
      "id": "satThresh",
      "name": "Saturation Threshold",
      "default": 0.4,
      "min": 0.0,
      "max": 1.0
    },
    {
      "id": "radius",
      "name": "Wave Radius",
      "default": 0.5,
      "min": 0.0,
      "max": 1.0
    },
    {
      "id": "pulseSpd",
      "name": "Pulse Speed",
      "default": 0.4,
      "min": 0.0,
      "max": 1.0
    },
    {
      "id": "depthInf",
      "name": "Depth Influence",
      "default": 0.5,
      "min": 0.0,
      "max": 1.0
    }
  ],
  "features": [
    "depth-aware",
    "temporal-persistence",
    "interactive",
    "colour-masking"
  ]
}