{
  "id": "gen-hyper-rainbow-vortex",
  "name": "Hyper Rainbow Vortex",
  "category": "generative",
  "url": "shaders/gen-hyper-rainbow-vortex.wgsl",
  "description": "A multi-layered chromatic vortex enriched with Wolfram Rankine fluid dynamics: solid-body rotation inside a bass-reactive core and irrotational flow outside. Angular velocity modulated by mids. Mouse spawns secondary vortices. Full upgraded-rgba stack with ACES tone mapping, temporal feedback, chromatic aberration, and semantic alpha.",
  "features": [
    "upgraded-rgba",
    "temporal",
    "audio-reactive",
    "mouse-driven"
  ],
  "tags": [
    "psychedelic",
    "neon",
    "vortex",
    "rainbow",
    "spiral",
    "chromatic",
    "fluid-dynamics",
    "rankine"
  ],
  "params": [
    {
      "id": "intensity",
      "name": "Intensity",
      "default": 0.7,
      "min": 0,
      "max": 1,
      "step": 0.01,
      "mapping": "zoom_params.x"
    },
    {
      "id": "speed",
      "name": "Speed",
      "default": 0.4,
      "min": 0,
      "max": 1,
      "step": 0.01,
      "mapping": "zoom_params.y"
    },
    {
      "id": "scale",
      "name": "Scale",
      "default": 0.5,
      "min": 0,
      "max": 1,
      "step": 0.01,
      "mapping": "zoom_params.z"
    },
    {
      "id": "colorshift",
      "name": "Color Shift",
      "default": 0,
      "min": 0,
      "max": 1,
      "step": 0.01,
      "mapping": "zoom_params.w"
    }
  ]
}
