{
  "id": "pixel-depth-sort",
  "name": "Pixel Depth Sort",
  "url": "shaders/pixel-depth-sort.wgsl",
  "category": "image",
  "description": "Simulates 3D depth by displacing pixels based on brightness. Features HDR gold rim lighting, ACES tone mapping, atmospheric fog, and depth-aware parallax. Mouse controls viewing perspective.",
  "params": [
    {
      "id": "depth",
      "name": "Depth Scale",
      "default": 0.5,
      "min": 0.0,
      "max": 1.0,
      "step": 0.01,
      "mapping": "zoom_params.x",
      "description": "Maximum displacement depth"
    },
    {
      "id": "shadows",
      "name": "Atmosphere",
      "default": 0.5,
      "min": 0.0,
      "max": 1.0,
      "step": 0.01,
      "mapping": "zoom_params.y",
      "description": "Atmospheric fog density and shadow strength"
    },
    {
      "id": "layers",
      "name": "Quality",
      "default": 0.5,
      "min": 0.0,
      "max": 1.0,
      "step": 0.01,
      "mapping": "zoom_params.z",
      "description": "Number of depth layers to sample"
    },
    {
      "id": "shadow_threshold",
      "name": "Rim Intensity",
      "default": 0.2,
      "min": 0.0,
      "max": 1.0,
      "step": 0.01,
      "mapping": "zoom_params.w",
      "description": "Strength of gold rim lighting on silhouette edges"
    }
  ],
  "features": [
    "mouse-driven",
    "depth-aware"
  ],
  "tags": [
    "filter",
    "image-processing",
    "depth-aware",
    "atmospheric",
    "HDR"
  ]
}
